notex/__init__.py
notex/commands.py
notex/convert.py
notex/exceptions.py
notex/pandoc_filters/extract_title.lua
notex-0.0.3.dist-info/LICENSE.txt
notex-0.0.3.dist-info/METADATA
notex-0.0.3.dist-info/WHEEL
notex-0.0.3.dist-info/entry_points.txt
notex-0.0.3.dist-info/top_level.txt
notex-0.0.3.dist-info/RECORD
