Metadata-Version: 2.1
Name: notex
Version: 0.0.3
Summary: Turning markdown notes with formulas into LaTeX PDFs 
Home-page: https://github.com/davidesarra/notex
Author: Davide Sarra
License: MIT
Keywords: markdown latex pdf python cli app
Platform: UNKNOWN
Classifier: Environment :: Console
Classifier: Intended Audience :: Developers
Classifier: Intended Audience :: Science/Research
Classifier: License :: OSI Approved :: MIT License
Classifier: Operating System :: OS Independent
Classifier: Programming Language :: Python :: 3
Classifier: Programming Language :: Python :: 3.6
Classifier: Programming Language :: Python :: 3.7
Classifier: Development Status :: 3 - Alpha 
Requires-Python: ~=3.6
Requires-Dist: Click (==7.0)
Requires-Dist: pypandoc (==1.4)
Provides-Extra: dev
Requires-Dist: black (==19.3b0) ; extra == 'dev'
Requires-Dist: flake8 (==3.7.8) ; extra == 'dev'
Requires-Dist: pytest (==5.1.3) ; extra == 'dev'
Requires-Dist: pytest-mock (==1.10.4) ; extra == 'dev'
